config/TestCfgReader.py
config/__init__.py
FrankLiPythonDemo-0.5.dist-info/METADATA
FrankLiPythonDemo-0.5.dist-info/WHEEL
FrankLiPythonDemo-0.5.dist-info/top_level.txt
FrankLiPythonDemo-0.5.dist-info/RECORD
