Metadata-Version: 2.1
Name: FrankLiPythonDemo
Version: 0.5
Summary: 李栋测试上传PyPI
Home-page: https://github.com/frankli/FrankLiPythonDemo
Author: 李栋
Author-email: frankli715@qq.com
